Implementation/IAS_Computer.v
module main(clk, endit);
	input clk;
	//Reg
	reg signed [0:11] PC = -1;
	reg signed [0:11] MAR;
	reg signed [0:19] IBR;
	reg signed [0:7] IR;
	reg signed [0:39] MBR;
	reg signed [0:39] AC;
	reg signed [0:39] MQ;
	//Memory reg
	reg signed [0:39] memory [0:999];
	//Temporary reg to store the result of multiplication.
	reg signed [0:79] mul;
	//Control signals
	reg fetch1 = 0;
	reg decode = 0;
	reg left = 0;
	reg execute = 0;
	reg rightleft = 0;
	reg jumpright = 0;
	reg incrementpc = 1;
	
	output endit;
	reg endit = 0;
	
	initial begin
  		$readmemb("memory.dat", memory);
	end
	
always@(negedge clk) begin	//Control signals handler
	if(fetch1 == 1) begin
		fetch1 = 0;
		decode = 1;
	end
	
	else if(decode == 1) begin
		decode = 0;
		execute = 1;
	end
	
	else if(execute == 1) begin
		execute = 0;
		if(left == 0) begin
			incrementpc = 1;
		end
		else begin
			left = 0;
			rightleft = 1;
		end
	end
	
	else if(incrementpc == 1) begin
		incrementpc = 0;
		PC = PC + 1;
		fetch1 = 1;
	end
	
	else if(rightleft == 1) begin
		rightleft = 0;
		execute = 1;
	end	
end 
		
always@(posedge clk) begin		//Fetch, decode and execute
	
	if(rightleft == 1) begin
		IR[0:7] = IBR[0:7];
		MAR[0:11] = IBR[8:19];
	end
	
	else if(fetch1 == 1)	begin		//Fetch
		MAR[0:11] = PC[0:11];
		MBR[0:39] = memory[MAR];
	end
	
	else if(decode == 1) begin		//Decode
		if(jumpright == 1) begin	//For right jump instructions
			MBR[0:19] = 20'b0;
			jumpright = 0;
		end
		
		if(MBR[0:19] == 20'b0) begin	//If no left instruction
			left = 0;
			IR = MBR[20:27];
			MAR = MBR[28:39];
		end
		else begin		//If left instruction is present
			left = 1;
			IBR = MBR[20:39];
			IR = MBR[0:7];
			MAR = MBR[8:19];
		end		
	end

	else if(execute == 1) begin		//Execute
		if(IR[0:7] == 8'b11111111) begin //HALT
			$writememb("Memory_out.dat", memory);
			endit = 1;
		end
			
		else if(IR[0:7] == 8'b00000001) begin //LOAD M(X)
			MBR[0:39] = memory[MAR];
			AC[0:39] = MBR[0:39];
		end
		
		else if(IR[0:7] == 8'b00000101) begin //ADD M(X)
			MBR[0:39] = memory[MAR];
			AC[0:39] = AC[0:39] + MBR[0:39];
		end
		
		else if(IR[0:7] == 8'b00100001) begin //STORE M(X)
			MBR[0:39] = AC[0:39];
			memory[MAR] = MBR[0:39];
		end	
		
		else if(IR[0:7] == 8'b00001010) begin //LOAD MQ
			AC[0:39] = MQ[0:39];
		end
		
		else if(IR[0:7] == 8'b00001001) begin //LOAD MQ, M(X)
			MBR[0:39] = memory[MAR];
			MQ[0:39] = MBR[0:39];
		end
		
		else if(IR[0:7] == 8'b00010100) begin //LSH
			AC = 2 * AC;
		end
		
		else if(IR[0:7] == 8'b00010101) begin //RSH
			AC = AC / 2;	
		end
		
		else if(IR[0:7] == 8'b00000010) begin // LOAD -M(X)
			MBR[0:39] = memory[MAR];
			AC[0:39] = MBR[0:39];
			AC[0:39] = -AC[0:39];
		end
		
		else if(IR[0:7] == 8'b00000110) begin //SUB M(X)
			MBR[0:39] = memory[MAR];
			AC = AC - MBR;
		end
		
		else if(IR[0:7] == 8'b00010010) begin //STORE M(X,8:19)
			MBR = AC[28:39];
			memory[MAR][8:19] = MBR;
		end
		
		else if(IR[0:7] == 8'b00010011) begin //STORE M(X,28:39)
			MBR = AC[28:39];
			memory[MAR][28:39] = MBR;
		end
		
		else if(IR[0:7] == 8'b00000011) begin //LOAD |M(X)|
			MBR[0:39] = memory[MAR];
			if(MBR[0] == 0)
				AC[0:39] = MBR[0:39];
			else
				AC[0:39] = -MBR[0:39];
		end
	
		else if(IR[0:7] == 8'b00000100) begin //LOAD -|M(X)|
			MBR[0:39] = memory[MAR];
			if(MBR[0] == 0)
				AC[0:39] = -MBR[0:39];
			else
				AC[0:39] = MBR[0:39];
		end
		
		else if(IR[0:7] == 8'b00000111) begin //ADD |M(X)|
			MBR[0:39] = memory[MAR];
			if(MBR[0] == 0)
				AC = AC	+ MBR;
			else 
				AC = AC - MBR;
		end
		
		else if(IR[0:7] == 8'b00001000) begin //SUB |M(X)|
			MBR[0:39] = memory[MAR];
			if(MBR[0] == 0)
				AC = AC - MBR;
			else
				AC = AC + MBR;
		end
		
		else if(IR[0:7] == 8'b00001011) begin // MUL M(X)
			MBR[0:39] = memory[MAR];
			mul[0:79] = MBR * MQ;
			AC[0:39] = mul[0:39];
			MQ[0:39] = mul[40:79];
		end 
		
		else if(IR[0:7] == 8'b00001100) begin // DIV M(X)
			MBR[0:39] = memory[MAR];
			MQ[0:39] = AC[0:39] / MBR[0:39];
			AC[0:39] = AC[0:39] % MBR[0:39];
		end 
		
		else if (IR[0:7] == 8'b00001101) begin //JUMP M(X,0:19)
			left = 0;
			PC = MAR - 1;
		end
		
		else if(IR[0:7] == 8'b00001110) begin //JUMP M(X,20:39)
			left = 0;
			PC = MAR - 1;
			jumpright = 1;
		end
		
		else if(IR[0:7] == 8'b00001111) begin //JUMP + M(X, 0:19)
			if(AC[0] == 0) begin
				left = 0;
				PC = MAR - 1;
			end
		end
		
		else if(IR[0:7] == 8'b00010000) begin //Jump + M(X, 20:39)
			if(AC[0] == 0) begin
				left = 0;
				PC = MAR - 1;
				jumpright = 1;
			end
		end		
	end
end

endmodule


`timescale 1ns/1ps

module test;			//Testbench

	reg clk;
	wire endit;
	
	main Implementation(clk, endit);
	
	initial begin
	
	$dumpfile("Output.vcd");
	$dumpvars(0, test);
		
	clk = 1; 
	
	end
	
	always begin
		#5 clk = ~clk;	
		if(endit == 1)
			$finish;	
	end
	
endmodule

Implementation/program1/Output.vcd
$date
	Tue Sep  1 19:58:46 2020
$end
$version
	Icarus Verilog
$end
$timescale
	1ps
$end
$scope module test $end
$var wire 1 ! endit $end
$var reg 1 " clk $end
$scope module Implementation $end
$var wire 1 " clk $end
$var reg 40 # AC [0:39] $end
$var reg 20 $ IBR [0:19] $end
$var reg 8 % IR [0:7] $end
$var reg 12 & MAR [0:11] $end
$var reg 40 ' MBR [0:39] $end
$var reg 40 ( MQ [0:39] $end
$var reg 12 ) PC [0:11] $end
$var reg 1 * decode $end
$var reg 1 ! endit $end
$var reg 1 + execute $end
$var reg 1 , fetch1 $end
$var reg 1 - incrementpc $end
$var reg 1 . jumpright $end
$var reg 1 / left $end
$var reg 80 0 mul [0:79] $end
$var reg 1 1 rightleft $end
$upscope $end
$upscope $end
$enddefinitions $end
#0
$dumpvars
01
bx 0
0/
0.
1-
0,
0+
0*
b111111111111 )
bx (
bx '
bx &
bx %
bx $
bx #
1"
0!
$end
#5000
1,
b0 )
0-
0"
#10000
b100000000010100000110000000000110 '
b0 &
1"
#15000
1*
0,
0"
#20000
b101 &
b1 %
b110000000000110 $
1/
1"
#25000
1+
0*
0"
#30000
b111 #
b111 '
1"
#35000
11
0/
0+
0"
#40000
b110 &
b110 %
1"
#45000
1+
01
0"
#50000
b101 #
b10 '
1"
#55000
1-
0+
0"
#60000
1"
#65000
1,
b1 )
0-
0"
#70000
b111100000000001100000001000000000101 '
b1 &
1"
#75000
1*
0,
0"
#80000
b11 &
b1111 %
b1000000000101 $
1/
1"
#85000
1+
0*
0"
#90000
b10 )
0/
1"
#95000
1-
0+
0"
#100000
1"
#105000
1,
b11 )
0-
0"
#110000
b100000000010100000110000000000110 '
1"
#115000
1*
0,
0"
#120000
b101 &
b1 %
b110000000000110 $
1/
1"
#125000
1+
0*
0"
#130000
b111 #
b111 '
1"
#135000
11
0/
0+
0"
#140000
b110 &
b110 %
1"
#145000
1+
01
0"
#150000
b101 #
b10 '
1"
#155000
1-
0+
0"
#160000
1"
#165000
1,
b100 )
0-
0"
#170000
b10000100000000100011111111000000000000 '
b100 &
1"
#175000
1*
0,
0"
#180000
b1000 &
b100001 %
b11111111000000000000 $
1/
1"
#185000
1+
0*
0"
#190000
b101 '
1"
#195000
11
0/
0+
0"
#200000
b0 &
b11111111 %
1"
#205000
1+
01
0"
#210000
1!
1"
#215000
1-
0+
0"
